{
  "configurations" : [
    {
      "nagios-env" : {
        "nagios_contact": "root@hdp.demo"
      }
    }
  ],
  "host_groups" : [
    {
      "name" : "host_group_1",     
      "components" : [
        {
          "name" : "HISTORYSERVER"
        },
        {
          "name" : "KAFKA_BROKER"
        },
        {
          "name" : "NAMENODE"
        },
        {
          "name" : "SUPERVISOR"
        },
        {
          "name" : "HCAT"
        },
        {
          "name" : "AMBARI_SERVER"
        },
        {
          "name" : "APP_TIMELINE_SERVER"
        },
        {
          "name" : "HDFS_CLIENT"
        },
        {
          "name" : "NODEMANAGER"
        },
        {
          "name" : "DATANODE"
        },
        {
          "name" : "WEBHCAT_SERVER"
        },
        {
          "name" : "RESOURCEMANAGER"
        },
        {
          "name" : "ZOOKEEPER_SERVER"
        },
        {
          "name" : "STORM_UI_SERVER"
        },
        {
          "name" : "HIVE_SERVER"
        },
        {
          "name" : "SECONDARY_NAMENODE"
        },
        {
          "name" : "HIVE_METASTORE"
        },
        {
          "name" : "MYSQL_SERVER"
        },
        {
          "name" : "DRPC_SERVER"
        },
        {
          "name" : "NIMBUS"
        }
      ],
      "cardinality" : "1"
    }
  ],
  "Blueprints" : {
    "stack_name" : "HDP",
    "stack_version" : "2.2"
  }
}
